mlhp.py
pymlhpcore.cpython-312-x86_64-linux-musl.so
mlhp.libs/libgcc_s-a3a07607.so.1
mlhp.libs/libstdc++-496613c0.so.6.0.32
mlhp.libs/libgomp-1f0f45f5.so.1.0.0
mlhp-0.1.2.dist-info/WHEEL
mlhp-0.1.2.dist-info/METADATA
mlhp-0.1.2.dist-info/RECORD
mlhp-0.1.2.dist-info/licenses/LICENSE
