Metadata-Version: 2.2
Name: mlhp
Version: 0.1.2
Summary: A work-in-progress finite element library.
Author: Philipp Kopp
Classifier: License :: OSI Approved :: MIT License
Project-URL: Homepage, https://gitlab.com/phmkopp/mlhp
Project-URL: Issues, https://github.com/phmkopp/mlhp/issues
